CPU/Reg2R1W.v
`timescale 1ns / 1ps


////////////////////////////////////////////////////////////////////////////////
// Company: Latvijas Universitāte
// Engineer: Andris Eihmanis
//
// Create Date:   12:32:04 04/01/2021
// Design Name:   Reg2R1W
// Module Name:   /home/ise/dip/Reg2R1W.v
// Project Name:  DIP RISC-V
// 
////////////////////////////////////////////////////////////////////////////////


module Reg2R1W(
    input [31:0] wrData,
    input [4:0] wrReg,
    input [4:0] readSelect1,
    input [4:0] readSelect2,
    output reg [31:0] readData1,
    output reg [31:0] readData2,
	 //output [31:0] readData1,
    //output [31:0] readData2,
    input clk,
    input writeEnable,
	 input rst
    );
	 
reg [31:0] RF [0:31];
integer index;

// RV32I Specification R0 = 0
//assign  readData1 = ( readSelect1 == 0 ) ? 0 : RF[readSelect1];
//assign  readData2 = ( readSelect2 == 0 ) ? 0 : RF[readSelect2];


//// Sync Reg read -- optional
// IF wrReg == readSelect1 => readData1 = wrData 
// IF wrReg == readSelect2 => readData2 = wrData
// 
	always @ (posedge clk) begin
		if (rst == 1) begin
          for(index = 0; index < 32; index = index + 1) 
			RF[index] <= 32'b0;
        end 
        else
          if(writeEnable) 
            begin
         //     $display("Write to %d:%d ", wrReg,wrData);
              RF[wrReg] <= wrData;
        	end
      
    end
	 
    always @ (posedge clk) begin
      if(wrReg == readSelect1)
        readData1 <= (writeEnable ? wrData : RF[readSelect1]);
      if(wrReg == readSelect2)
        readData2 <= (writeEnable ? wrData : RF[readSelect2]);
		if (!writeEnable) begin
			readData1 <= ( readSelect1 == 0 ) ? 0 : RF[readSelect1];
			// $display("PRG:Read to %d:%d ", readSelect1,readData1);
			readData2 <= ( readSelect2 == 0 ) ? 0 : RF[readSelect2];
      	//$display("PRG:Read to %d:%d ", readSelect1,readData1);
      end
	end

endmodule

CPU/TB_Reg.v
`timescale 1ns / 1ps

////////////////////////////////////////////////////////////////////////////////
// Company: Latvijas Universitāte
// Engineer: Andris Eihmanis
//
// Create Date:   12:37:04 04/01/2021
// Design Name:   Reg2R1W
// Module Name:   /home/ise/dip/TB_Reg.v
// Project Name:  DIP RISC-V
// 
////////////////////////////////////////////////////////////////////////////////

module TB_Reg;

	// Inputs
	reg [31:0] wrData;
	reg [4:0] wrReg;
	reg [4:0] readSelect1;
	reg [4:0] readSelect2;
	reg clk;
	reg writeEnable;
	reg rst;

	// Outputs
	wire [31:0] readData1;
	wire [31:0] readData2;

	// Instantiate the Unit Under Test (UUT)
	Reg2R1W uut (
		.wrData(wrData), 
		.wrReg(wrReg), 
		.readSelect1(readSelect1), 
		.readSelect2(readSelect2), 
		.readData1(readData1), 
		.readData2(readData2), 
		.clk(clk), 
		.writeEnable(writeEnable), 
		.rst(rst)
	);

	integer index;

initial begin
	// Initialize Inputs
	wrData = 0;
	wrReg = 0;
	readSelect1 = 0;
	readSelect2 = 0;
	clk = 0;
	writeEnable = 0;
	rst = 0;

	// Wait 100 ns for global reset to finish
	#100;
        
		// Add stimulus here
end
	
always #10 clk=!clk;
  
initial
begin
	#100; /// initial shift
	$dumpfile ("R2W1v2.vcd"); $dumpvars(0,TB_Reg);
	#5 rst=1;
	writeEnable=0;
	#10 rst=0;
end
	
initial
begin
	#100; /// initial shift
	#14
	
// Test - Write Register File;
	for(index=0;index<32;index=index+1)
	begin
		 wrReg = index;
		 wrData = 16*index;
		 $display("wrReg: %d wrData:%d",wrReg, wrData);
		 writeEnable = 1;
		 #20;
		 writeEnable = 0;
	end
	
	#50
      
      
// Test - Read Reg file and output Even and Odd reg RF[]=> R1 & R2		
    for (index = 0; index < 32; index = index + 2)
      begin
			readSelect1 = index;
			readSelect2 = index + 1;
			#20;
			$display ("REG[%2d]=%d, REG[%2d]=%d",readSelect1,readData1,readSelect2,readData2);
		end
     	#20;
     
// Test - Read R0;
     	readSelect1 = 0;
     	readSelect2 = 0;
		#20;
		$display ("-= REG[%2d]=%d, REG[%2d]=%d",readSelect1,readData1,readSelect2,readData2);
		#20;

// Test - Write and Read sync; WR->R1 && R2
      for(index=0;index<32;index=index+1)
		begin
          wrReg = index;
          readSelect1 = index;
          readSelect2 = index;
          wrData = 16*index;
          writeEnable = 1;
          #20;
          $display("wrReg: %d wrData:%d readSelect1:%d readData1: %d",wrReg, wrData, readSelect1,readData1);
          #20;
          writeEnable = 0;
		end

		#50;
		#2000 $finish;
    end
endmodule

CPU/R2W1v2.vcd
$date
   Thu Apr 15 15:21:19 2021
$end
$version
  P.20131013
$end
$timescale
  1ps
$end
$scope module TB_Reg $end
$var wire 1 ! readData1 [31] $end
$var wire 1 " readData1 [30] $end
$var wire 1 # readData1 [29] $end
$var wire 1 $ readData1 [28] $end
$var wire 1 % readData1 [27] $end
$var wire 1 & readData1 [26] $end
$var wire 1 ' readData1 [25] $end
$var wire 1 ( readData1 [24] $end
$var wire 1 ) readData1 [23] $end
$var wire 1 * readData1 [22] $end
$var wire 1 + readData1 [21] $end
$var wire 1 , readData1 [20] $end
$var wire 1 - readData1 [19] $end
$var wire 1 . readData1 [18] $end
$var wire 1 / readData1 [17] $end
$var wire 1 0 readData1 [16] $end
$var wire 1 1 readData1 [15] $end
$var wire 1 2 readData1 [14] $end
$var wire 1 3 readData1 [13] $end
$var wire 1 4 readData1 [12] $end
$var wire 1 5 readData1 [11] $end
$var wire 1 6 readData1 [10] $end
$var wire 1 7 readData1 [9] $end
$var wire 1 8 readData1 [8] $end
$var wire 1 9 readData1 [7] $end
$var wire 1 : readData1 [6] $end
$var wire 1 ; readData1 [5] $end
$var wire 1 < readData1 [4] $end
$var wire 1 = readData1 [3] $end
$var wire 1 > readData1 [2] $end
$var wire 1 ? readData1 [1] $end
$var wire 1 @ readData1 [0] $end
$var wire 1 A readData2 [31] $end
$var wire 1 B readData2 [30] $end
$var wire 1 C readData2 [29] $end
$var wire 1 D readData2 [28] $end
$var wire 1 E readData2 [27] $end
$var wire 1 F readData2 [26] $end
$var wire 1 G readData2 [25] $end
$var wire 1 H readData2 [24] $end
$var wire 1 I readData2 [23] $end
$var wire 1 J readData2 [22] $end
$var wire 1 K readData2 [21] $end
$var wire 1 L readData2 [20] $end
$var wire 1 M readData2 [19] $end
$var wire 1 N readData2 [18] $end
$var wire 1 O readData2 [17] $end
$var wire 1 P readData2 [16] $end
$var wire 1 Q readData2 [15] $end
$var wire 1 R readData2 [14] $end
$var wire 1 S readData2 [13] $end
$var wire 1 T readData2 [12] $end
$var wire 1 U readData2 [11] $end
$var wire 1 V readData2 [10] $end
$var wire 1 W readData2 [9] $end
$var wire 1 X readData2 [8] $end
$var wire 1 Y readData2 [7] $end
$var wire 1 Z readData2 [6] $end
$var wire 1 [ readData2 [5] $end
$var wire 1 \ readData2 [4] $end
$var wire 1 ] readData2 [3] $end
$var wire 1 ^ readData2 [2] $end
$var wire 1 _ readData2 [1] $end
$var wire 1 ` readData2 [0] $end
$var reg 32 a wrData [31:0] $end
$var reg 5 b wrReg [4:0] $end
$var reg 5 c readSelect1 [4:0] $end
$var reg 5 d readSelect2 [4:0] $end
$var reg 1 e clk $end
$var reg 1 f writeEnable $end
$var reg 1 g rst $end
$var integer 32 h index $end
$scope module uut $end
$var wire 1 i wrData [31] $end
$var wire 1 j wrData [30] $end
$var wire 1 k wrData [29] $end
$var wire 1 l wrData [28] $end
$var wire 1 m wrData [27] $end
$var wire 1 n wrData [26] $end
$var wire 1 o wrData [25] $end
$var wire 1 p wrData [24] $end
$var wire 1 q wrData [23] $end
$var wire 1 r wrData [22] $end
$var wire 1 s wrData [21] $end
$var wire 1 t wrData [20] $end
$var wire 1 u wrData [19] $end
$var wire 1 v wrData [18] $end
$var wire 1 w wrData [17] $end
$var wire 1 x wrData [16] $end
$var wire 1 y wrData [15] $end
$var wire 1 z wrData [14] $end
$var wire 1 { wrData [13] $end
$var wire 1 | wrData [12] $end
$var wire 1 } wrData [11] $end
$var wire 1 ~ wrData [10] $end
$var wire 1 !! wrData [9] $end
$var wire 1 "! wrData [8] $end
$var wire 1 #! wrData [7] $end
$var wire 1 $! wrData [6] $end
$var wire 1 %! wrData [5] $end
$var wire 1 &! wrData [4] $end
$var wire 1 '! wrData [3] $end
$var wire 1 (! wrData [2] $end
$var wire 1 )! wrData [1] $end
$var wire 1 *! wrData [0] $end
$var wire 1 +! wrReg [4] $end
$var wire 1 ,! wrReg [3] $end
$var wire 1 -! wrReg [2] $end
$var wire 1 .! wrReg [1] $end
$var wire 1 /! wrReg [0] $end
$var wire 1 0! readSelect1 [4] $end
$var wire 1 1! readSelect1 [3] $end
$var wire 1 2! readSelect1 [2] $end
$var wire 1 3! readSelect1 [1] $end
$var wire 1 4! readSelect1 [0] $end
$var wire 1 5! readSelect2 [4] $end
$var wire 1 6! readSelect2 [3] $end
$var wire 1 7! readSelect2 [2] $end
$var wire 1 8! readSelect2 [1] $end
$var wire 1 9! readSelect2 [0] $end
$var wire 1 :! clk $end
$var wire 1 ;! writeEnable $end
$var wire 1 <! rst $end
$var reg 32 =! readData1 [31:0] $end
$var reg 32 >! readData2 [31:0] $end
$var reg 1024 ?! RF [31:0] $end
$var integer 32 @! index $end
$upscope $end
$upscope $end
$enddefinitions $end
#100000
$dumpvars
09
08
0)!
07
0*!
0@
0?
0>
0=
0<
0;
0:
0(!
0'!
0&!
0%!
0$!
0#!
0"!
0!!
0~
0}
0|
0{
0z
0y
0x
0w
0v
0u
0t
0s
0r
0q
0p
0o
0n
0m
0l
0k
0j
0i
0/!
b0 a
b0 b
b0 c
b0 d
0e
0f
0g
bx h
06
05
04
03
02
01
00
0/
0.
0-
0,
0+
0*
0)
0(
0'
0&
0%
0$
0#
0"
0!
0`
0_
0^
0]
0\
0[
0Z
0Y
0X
0W
0V
0U
0T
0S
0R
0Q
0P
0O
0N
0M
0L
0K
0J
0I
0H
0G
0F
0E
0D
0C
0B
0A
b0 =!
b0 >!
bx ?!
bx @!
0.!
0-!
0,!
0+!
04!
03!
02!
01!
00!
09!
08!
07!
06!
05!
0:!
0;!
0<!
$end
#105000
1g
1<!
#110000
1e
b0 =!
b0 >!
b0 ?!
b100000 @!
1:!
#114000
1f
b0 h
1;!
#115000
0g
0<!
#120000
0e
0:!
#130000
1e
1:!
#134000
1&!
1/!
b10000 a
b1 b
1f
b1 h
#140000
0e
0:!
#150000
1e
b10000000000000000000000000000000000000000000000000000000000000000000000000000000000000000000000000000000000000000000000000000000000000000000000000000000000000000000000000000000000000000000000000000000000000000000000000000000000000000000000000000000000000000000000000000000000000000000000000000000000000000000000000000000000000000000000000000000000000000000000000000000000000000000000000000000000000000000000000000000000000000000000000000000000000000000000000000000000000000000000000000000000000000000000000000000000000000000000000000000000000000000000000000000000000000000000000000000000000000000000000000000000000000000000000000000000000000000000000000000000000000000000000000000000000000000000000000000000000000000000000000000000000000000000000000000000000000000000000000000000000000000000000000000000000000000000000000000000000000000000000000000000000000000000000000000000000000000000000000000000000000000000000000000000000000000000000000000000000000000000000000 ?!
1:!
#154000
0&!
1%!
0/!
b100000 a
b10 b
1f
b10 h
1.!
#160000
0e
0:!
#170000
1e
b10000000000000000000000000000001000000000000000000000000000000000000000000000000000000000000000000000000000000000000000000000000000000000000000000000000000000000000000000000000000000000000000000000000000000000000000000000000000000000000000000000000000000000000000000000000000000000000000000000000000000000000000000000000000000000000000000000000000000000000000000000000000000000000000000000000000000000000000000000000000000000000000000000000000000000000000000000000000000000000000000000000000000000000000000000000000000000000000000000000000000000000000000000000000000000000000000000000000000000000000000000000000000000000000000000000000000000000000000000000000000000000000000000000000000000000000000000000000000000000000000000000000000000000000000000000000000000000000000000000000000000000000000000000000000000000000000000000000000000000000000000000000000000000000000000000000000000000000000000000000000000000000000000000000000000000000000000000000000000000000000000 ?!
1:!
#174000
1&!
1/!
b110000 a
b11 b
1f
b11 h
#180000
0e
0:!
#190000
1e
b10000000000000000000000000000001000000000000000000000000000000011000000000000000000000000000000000000000000000000000000000000000000000000000000000000000000000000000000000000000000000000000000000000000000000000000000000000000000000000000000000000000000000000000000000000000000000000000000000000000000000000000000000000000000000000000000000000000000000000000000000000000000000000000000000000000000000000000000000000000000000000000000000000000000000000000000000000000000000000000000000000000000000000000000000000000000000000000000000000000000000000000000000000000000000000000000000000000000000000000000000000000000000000000000000000000000000000000000000000000000000000000000000000000000000000000000000000000000000000000000000000000000000000000000000000000000000000000000000000000000000000000000000000000000000000000000000000000000000000000000000000000000000000000000000000000000000000000000000000000000000000000000000000000000000000000000000000000000000000000000000000 ?!
1:!
#194000
0&!
0%!
1$!
0/!
b1000000 a
b100 b
1f
b100 h
0.!
1-!
#200000
0e
0:!
#210000
1e
b10000000000000000000000000000001000000000000000000000000000000011000000000000000000000000000001000000000000000000000000000000000000000000000000000000000000000000000000000000000000000000000000000000000000000000000000000000000000000000000000000000000000000000000000000000000000000000000000000000000000000000000000000000000000000000000000000000000000000000000000000000000000000000000000000000000000000000000000000000000000000000000000000000000000000000000000000000000000000000000000000000000000000000000000000000000000000000000000000000000000000000000000000000000000000000000000000000000000000000000000000000000000000000000000000000000000000000000000000000000000000000000000000000000000000000000000000000000000000000000000000000000000000000000000000000000000000000000000000000000000000000000000000000000000000000000000000000000000000000000000000000000000000000000000000000000000000000000000000000000000000000000000000000000000000000000000000000000000000000000000000000 ?!
1:!
#214000
1&!
1/!
b1010000 a
b101 b
1f
b101 h
#220000
0e
0:!
#230000
1e
b10000000000000000000000000000001000000000000000000000000000000011000000000000000000000000000001000000000000000000000000000000010100000000000000000000000000000000000000000000000000000000000000000000000000000000000000000000000000000000000000000000000000000000000000000000000000000000000000000000000000000000000000000000000000000000000000000000000000000000000000000000000000000000000000000000000000000000000000000000000000000000000000000000000000000000000000000000000000000000000000000000000000000000000000000000000000000000000000000000000000000000000000000000000000000000000000000000000000000000000000000000000000000000000000000000000000000000000000000000000000000000000000000000000000000000000000000000000000000000000000000000000000000000000000000000000000000000000000000000000000000000000000000000000000000000000000000000000000000000000000000000000000000000000000000000000000000000000000000000000000000000000000000000000000000000000000000000000000000000000000000000 ?!
1:!
#234000
0&!
1%!
0/!
b1100000 a
b110 b
1f
b110 h
1.!
#240000
0e
0:!
#250000
1e
b10000000000000000000000000000001000000000000000000000000000000011000000000000000000000000000001000000000000000000000000000000010100000000000000000000000000000110000000000000000000000000000000000000000000000000000000000000000000000000000000000000000000000000000000000000000000000000000000000000000000000000000000000000000000000000000000000000000000000000000000000000000000000000000000000000000000000000000000000000000000000000000000000000000000000000000000000000000000000000000000000000000000000000000000000000000000000000000000000000000000000000000000000000000000000000000000000000000000000000000000000000000000000000000000000000000000000000000000000000000000000000000000000000000000000000000000000000000000000000000000000000000000000000000000000000000000000000000000000000000000000000000000000000000000000000000000000000000000000000000000000000000000000000000000000000000000000000000000000000000000000000000000000000000000000000000000000000000000000000000000000000 ?!
1:!
#254000
1&!
1/!
b1110000 a
b111 b
1f
b111 h
#260000
0e
0:!
#270000
1e
b10000000000000000000000000000001000000000000000000000000000000011000000000000000000000000000001000000000000000000000000000000010100000000000000000000000000000110000000000000000000000000000001110000000000000000000000000000000000000000000000000000000000000000000000000000000000000000000000000000000000000000000000000000000000000000000000000000000000000000000000000000000000000000000000000000000000000000000000000000000000000000000000000000000000000000000000000000000000000000000000000000000000000000000000000000000000000000000000000000000000000000000000000000000000000000000000000000000000000000000000000000000000000000000000000000000000000000000000000000000000000000000000000000000000000000000000000000000000000000000000000000000000000000000000000000000000000000000000000000000000000000000000000000000000000000000000000000000000000000000000000000000000000000000000000000000000000000000000000000000000000000000000000000000000000000000000000000000000000000000000000000 ?!
1:!
#274000
0&!
0%!
0$!
1#!
0/!
b10000000 a
b1000 b
1f
b1000 h
0.!
0-!
1,!
#280000
0e
0:!
#290000
1e
b10000000000000000000000000000001000000000000000000000000000000011000000000000000000000000000001000000000000000000000000000000010100000000000000000000000000000110000000000000000000000000000001110000000000000000000000000000100000000000000000000000000000000000000000000000000000000000000000000000000000000000000000000000000000000000000000000000000000000000000000000000000000000000000000000000000000000000000000000000000000000000000000000000000000000000000000000000000000000000000000000000000000000000000000000000000000000000000000000000000000000000000000000000000000000000000000000000000000000000000000000000000000000000000000000000000000000000000000000000000000000000000000000000000000000000000000000000000000000000000000000000000000000000000000000000000000000000000000000000000000000000000000000000000000000000000000000000000000000000000000000000000000000000000000000000000000000000000000000000000000000000000000000000000000000000000000000000000000000000000000000000 ?!
1:!
#294000
1&!
1/!
b10010000 a
b1001 b
1f
b1001 h
#300000
0e
0:!
#310000
1e
b10000000000000000000000000000001000000000000000000000000000000011000000000000000000000000000001000000000000000000000000000000010100000000000000000000000000000110000000000000000000000000000001110000000000000000000000000000100000000000000000000000000000001001000000000000000000000000000000000000000000000000000000000000000000000000000000000000000000000000000000000000000000000000000000000000000000000000000000000000000000000000000000000000000000000000000000000000000000000000000000000000000000000000000000000000000000000000000000000000000000000000000000000000000000000000000000000000000000000000000000000000000000000000000000000000000000000000000000000000000000000000000000000000000000000000000000000000000000000000000000000000000000000000000000000000000000000000000000000000000000000000000000000000000000000000000000000000000000000000000000000000000000000000000000000000000000000000000000000000000000000000000000000000000000000000000000000000000000000000000000000000 ?!
1:!
#314000
0&!
1%!
0/!
b10100000 a
b1010 b
1f
b1010 h
1.!
#320000
0e
0:!
#330000
1e
b10000000000000000000000000000001000000000000000000000000000000011000000000000000000000000000001000000000000000000000000000000010100000000000000000000000000000110000000000000000000000000000001110000000000000000000000000000100000000000000000000000000000001001000000000000000000000000000010100000000000000000000000000000000000000000000000000000000000000000000000000000000000000000000000000000000000000000000000000000000000000000000000000000000000000000000000000000000000000000000000000000000000000000000000000000000000000000000000000000000000000000000000000000000000000000000000000000000000000000000000000000000000000000000000000000000000000000000000000000000000000000000000000000000000000000000000000000000000000000000000000000000000000000000000000000000000000000000000000000000000000000000000000000000000000000000000000000000000000000000000000000000000000000000000000000000000000000000000000000000000000000000000000000000000000000000000000000000000000000000000000000 ?!
1:!
#334000
1&!
1/!
b10110000 a
b1011 b
1f
b1011 h
#340000
0e
0:!
#350000
1e
b10000000000000000000000000000001000000000000000000000000000000011000000000000000000000000000001000000000000000000000000000000010100000000000000000000000000000110000000000000000000000000000001110000000000000000000000000000100000000000000000000000000000001001000000000000000000000000000010100000000000000000000000000000101100000000000000000000000000000000000000000000000000000000000000000000000000000000000000000000000000000000000000000000000000000000000000000000000000000000000000000000000000000000000000000000000000000000000000000000000000000000000000000000000000000000000000000000000000000000000000000000000000000000000000000000000000000000000000000000000000000000000000000000000000000000000000000000000000000000000000000000000000000000000000000000000000000000000000000000000000000000000000000000000000000000000000000000000000000000000000000000000000000000000000000000000000000000000000000000000000000000000000000000000000000000000000000000000000000000000000000000 ?!
1:!
#354000
0&!
0%!
1$!
0/!
b11000000 a
b1100 b
1f
b1100 h
0.!
1-!
#360000
0e
0:!
#370000
1e
b10000000000000000000000000000001000000000000000000000000000000011000000000000000000000000000001000000000000000000000000000000010100000000000000000000000000000110000000000000000000000000000001110000000000000000000000000000100000000000000000000000000000001001000000000000000000000000000010100000000000000000000000000000101100000000000000000000000000001100000000000000000000000000000000000000000000000000000000000000000000000000000000000000000000000000000000000000000000000000000000000000000000000000000000000000000000000000000000000000000000000000000000000000000000000000000000000000000000000000000000000000000000000000000000000000000000000000000000000000000000000000000000000000000000000000000000000000000000000000000000000000000000000000000000000000000000000000000000000000000000000000000000000000000000000000000000000000000000000000000000000000000000000000000000000000000000000000000000000000000000000000000000000000000000000000000000000000000000000000000000000000 ?!
1:!
#374000
1&!
1/!
b11010000 a
b1101 b
1f
b1101 h
#380000
0e
0:!
#390000
1e
b10000000000000000000000000000001000000000000000000000000000000011000000000000000000000000000001000000000000000000000000000000010100000000000000000000000000000110000000000000000000000000000001110000000000000000000000000000100000000000000000000000000000001001000000000000000000000000000010100000000000000000000000000000101100000000000000000000000000001100000000000000000000000000000011010000000000000000000000000000000000000000000000000000000000000000000000000000000000000000000000000000000000000000000000000000000000000000000000000000000000000000000000000000000000000000000000000000000000000000000000000000000000000000000000000000000000000000000000000000000000000000000000000000000000000000000000000000000000000000000000000000000000000000000000000000000000000000000000000000000000000000000000000000000000000000000000000000000000000000000000000000000000000000000000000000000000000000000000000000000000000000000000000000000000000000000000000000000000000000000000000000 ?!
1:!
#394000
0&!
1%!
0/!
b11100000 a
b1110 b
1f
b1110 h
1.!
#400000
0e
0:!
#410000
1e
b10000000000000000000000000000001000000000000000000000000000000011000000000000000000000000000001000000000000000000000000000000010100000000000000000000000000000110000000000000000000000000000001110000000000000000000000000000100000000000000000000000000000001001000000000000000000000000000010100000000000000000000000000000101100000000000000000000000000001100000000000000000000000000000011010000000000000000000000000000111000000000000000000000000000000000000000000000000000000000000000000000000000000000000000000000000000000000000000000000000000000000000000000000000000000000000000000000000000000000000000000000000000000000000000000000000000000000000000000000000000000000000000000000000000000000000000000000000000000000000000000000000000000000000000000000000000000000000000000000000000000000000000000000000000000000000000000000000000000000000000000000000000000000000000000000000000000000000000000000000000000000000000000000000000000000000000000000000000000000000000000000 ?!
1:!
#414000
1&!
1/!
b11110000 a
b1111 b
1f
b1111 h
#420000
0e
0:!
#430000
1e
b10000000000000000000000000000001000000000000000000000000000000011000000000000000000000000000001000000000000000000000000000000010100000000000000000000000000000110000000000000000000000000000001110000000000000000000000000000100000000000000000000000000000001001000000000000000000000000000010100000000000000000000000000000101100000000000000000000000000001100000000000000000000000000000011010000000000000000000000000000111000000000000000000000000000001111000000000000000000000000000000000000000000000000000000000000000000000000000000000000000000000000000000000000000000000000000000000000000000000000000000000000000000000000000000000000000000000000000000000000000000000000000000000000000000000000000000000000000000000000000000000000000000000000000000000000000000000000000000000000000000000000000000000000000000000000000000000000000000000000000000000000000000000000000000000000000000000000000000000000000000000000000000000000000000000000000000000000000000000000000000000000 ?!
1:!
#434000
0&!
0%!
0$!
0#!
1"!
0/!
b100000000 a
b10000 b
1f
b10000 h
0.!
0-!
0,!
1+!
#440000
0e
0:!
#450000
1e
b10000000000000000000000000000001000000000000000000000000000000011000000000000000000000000000001000000000000000000000000000000010100000000000000000000000000000110000000000000000000000000000001110000000000000000000000000000100000000000000000000000000000001001000000000000000000000000000010100000000000000000000000000000101100000000000000000000000000001100000000000000000000000000000011010000000000000000000000000000111000000000000000000000000000001111000000000000000000000000000100000000000000000000000000000000000000000000000000000000000000000000000000000000000000000000000000000000000000000000000000000000000000000000000000000000000000000000000000000000000000000000000000000000000000000000000000000000000000000000000000000000000000000000000000000000000000000000000000000000000000000000000000000000000000000000000000000000000000000000000000000000000000000000000000000000000000000000000000000000000000000000000000000000000000000000000000000000000000000000000000000000 ?!
1:!
#454000
1&!
1/!
b100010000 a
b10001 b
1f
b10001 h
#460000
0e
0:!
#470000
1e
b10000000000000000000000000000001000000000000000000000000000000011000000000000000000000000000001000000000000000000000000000000010100000000000000000000000000000110000000000000000000000000000001110000000000000000000000000000100000000000000000000000000000001001000000000000000000000000000010100000000000000000000000000000101100000000000000000000000000001100000000000000000000000000000011010000000000000000000000000000111000000000000000000000000000001111000000000000000000000000000100000000000000000000000000000001000100000000000000000000000000000000000000000000000000000000000000000000000000000000000000000000000000000000000000000000000000000000000000000000000000000000000000000000000000000000000000000000000000000000000000000000000000000000000000000000000000000000000000000000000000000000000000000000000000000000000000000000000000000000000000000000000000000000000000000000000000000000000000000000000000000000000000000000000000000000000000000000000000000000000000000000 ?!
1:!
#474000
0&!
1%!
0/!
b100100000 a
b10010 b
1f
b10010 h
1.!
#480000
0e
0:!
#490000
1e
b10000000000000000000000000000001000000000000000000000000000000011000000000000000000000000000001000000000000000000000000000000010100000000000000000000000000000110000000000000000000000000000001110000000000000000000000000000100000000000000000000000000000001001000000000000000000000000000010100000000000000000000000000000101100000000000000000000000000001100000000000000000000000000000011010000000000000000000000000000111000000000000000000000000000001111000000000000000000000000000100000000000000000000000000000001000100000000000000000000000000010010000000000000000000000000000000000000000000000000000000000000000000000000000000000000000000000000000000000000000000000000000000000000000000000000000000000000000000000000000000000000000000000000000000000000000000000000000000000000000000000000000000000000000000000000000000000000000000000000000000000000000000000000000000000000000000000000000000000000000000000000000000000000000000000000000000000000000000000000000000000000 ?!
1:!
#494000
1&!
1/!
b100110000 a
b10011 b
1f
b10011 h
#500000
0e
0:!
#510000
1e
b10000000000000000000000000000001000000000000000000000000000000011000000000000000000000000000001000000000000000000000000000000010100000000000000000000000000000110000000000000000000000000000001110000000000000000000000000000100000000000000000000000000000001001000000000000000000000000000010100000000000000000000000000000101100000000000000000000000000001100000000000000000000000000000011010000000000000000000000000000111000000000000000000000000000001111000000000000000000000000000100000000000000000000000000000001000100000000000000000000000000010010000000000000000000000000000100110000000000000000000000000000000000000000000000000000000000000000000000000000000000000000000000000000000000000000000000000000000000000000000000000000000000000000000000000000000000000000000000000000000000000000000000000000000000000000000000000000000000000000000000000000000000000000000000000000000000000000000000000000000000000000000000000000000000000000000000000000000000000000000000000000 ?!
1:!
#514000
0&!
0%!
1$!
0/!
b101000000 a
b10100 b
1f
b10100 h
0.!
1-!
#520000
0e
0:!
#530000
1e
b10000000000000000000000000000001000000000000000000000000000000011000000000000000000000000000001000000000000000000000000000000010100000000000000000000000000000110000000000000000000000000000001110000000000000000000000000000100000000000000000000000000000001001000000000000000000000000000010100000000000000000000000000000101100000000000000000000000000001100000000000000000000000000000011010000000000000000000000000000111000000000000000000000000000001111000000000000000000000000000100000000000000000000000000000001000100000000000000000000000000010010000000000000000000000000000100110000000000000000000000000001010000000000000000000000000000000000000000000000000000000000000000000000000000000000000000000000000000000000000000000000000000000000000000000000000000000000000000000000000000000000000000000000000000000000000000000000000000000000000000000000000000000000000000000000000000000000000000000000000000000000000000000000000000000000000000000000000000000000000000000000 ?!
1:!
#534000
1&!
1/!
b101010000 a
b10101 b
1f
b10101 h
#540000
0e
0:!
#550000
1e
b10000000000000000000000000000001000000000000000000000000000000011000000000000000000000000000001000000000000000000000000000000010100000000000000000000000000000110000000000000000000000000000001110000000000000000000000000000100000000000000000000000000000001001000000000000000000000000000010100000000000000000000000000000101100000000000000000000000000001100000000000000000000000000000011010000000000000000000000000000111000000000000000000000000000001111000000000000000000000000000100000000000000000000000000000001000100000000000000000000000000010010000000000000000000000000000100110000000000000000000000000001010000000000000000000000000000010101000000000000000000000000000000000000000000000000000000000000000000000000000000000000000000000000000000000000000000000000000000000000000000000000000000000000000000000000000000000000000000000000000000000000000000000000000000000000000000000000000000000000000000000000000000000000000000000000000000000000000000000000000000000000 ?!
1:!
#554000
0&!
1%!
0/!
b101100000 a
b10110 b
1f
b10110 h
1.!
#560000
0e
0:!
#570000
1e
b10000000000000000000000000000001000000000000000000000000000000011000000000000000000000000000001000000000000000000000000000000010100000000000000000000000000000110000000000000000000000000000001110000000000000000000000000000100000000000000000000000000000001001000000000000000000000000000010100000000000000000000000000000101100000000000000000000000000001100000000000000000000000000000011010000000000000000000000000000111000000000000000000000000000001111000000000000000000000000000100000000000000000000000000000001000100000000000000000000000000010010000000000000000000000000000100110000000000000000000000000001010000000000000000000000000000010101000000000000000000000000000101100000000000000000000000000000000000000000000000000000000000000000000000000000000000000000000000000000000000000000000000000000000000000000000000000000000000000000000000000000000000000000000000000000000000000000000000000000000000000000000000000000000000000000000000000000000000000000000000000000 ?!
1:!
#574000
1&!
1/!
b101110000 a
b10111 b
1f
b10111 h
#580000
0e
0:!
#590000
1e
b10000000000000000000000000000001000000000000000000000000000000011000000000000000000000000000001000000000000000000000000000000010100000000000000000000000000000110000000000000000000000000000001110000000000000000000000000000100000000000000000000000000000001001000000000000000000000000000010100000000000000000000000000000101100000000000000000000000000001100000000000000000000000000000011010000000000000000000000000000111000000000000000000000000000001111000000000000000000000000000100000000000000000000000000000001000100000000000000000000000000010010000000000000000000000000000100110000000000000000000000000001010000000000000000000000000000010101000000000000000000000000000101100000000000000000000000000001011100000000000000000000000000000000000000000000000000000000000000000000000000000000000000000000000000000000000000000000000000000000000000000000000000000000000000000000000000000000000000000000000000000000000000000000000000000000000000000000000000000000000000000000 ?!
1:!
#594000
0&!
0%!
0$!
1#!
0/!
b110000000 a
b11000 b
1f
b11000 h
0.!
0-!
1,!
#600000
0e
0:!
#610000
1e
b10000000000000000000000000000001000000000000000000000000000000011000000000000000000000000000001000000000000000000000000000000010100000000000000000000000000000110000000000000000000000000000001110000000000000000000000000000100000000000000000000000000000001001000000000000000000000000000010100000000000000000000000000000101100000000000000000000000000001100000000000000000000000000000011010000000000000000000000000000111000000000000000000000000000001111000000000000000000000000000100000000000000000000000000000001000100000000000000000000000000010010000000000000000000000000000100110000000000000000000000000001010000000000000000000000000000010101000000000000000000000000000101100000000000000000000000000001011100000000000000000000000000011000000000000000000000000000000000000000000000000000000000000000000000000000000000000000000000000000000000000000000000000000000000000000000000000000000000000000000000000000000000000000000000000000000000000000000000000000000000000000 ?!
1:!
#614000
1&!
1/!
b110010000 a
b11001 b
1f
b11001 h
#620000
0e
0:!
#630000
1e
b10000000000000000000000000000001000000000000000000000000000000011000000000000000000000000000001000000000000000000000000000000010100000000000000000000000000000110000000000000000000000000000001110000000000000000000000000000100000000000000000000000000000001001000000000000000000000000000010100000000000000000000000000000101100000000000000000000000000001100000000000000000000000000000011010000000000000000000000000000111000000000000000000000000000001111000000000000000000000000000100000000000000000000000000000001000100000000000000000000000000010010000000000000000000000000000100110000000000000000000000000001010000000000000000000000000000010101000000000000000000000000000101100000000000000000000000000001011100000000000000000000000000011000000000000000000000000000000110010000000000000000000000000000000000000000000000000000000000000000000000000000000000000000000000000000000000000000000000000000000000000000000000000000000000000000000000000000000000000000000000000000 ?!
1:!
#634000
0&!
1%!
0/!
b110100000 a
b11010 b
1f
b11010 h
1.!
#640000
0e
0:!
